obs/__init__.py
obs/chapters_and_frames.py
obs/export_to_tex.py
obs/obs_classes.py
obs_tools-0.0.4.dist-info/DESCRIPTION.rst
obs_tools-0.0.4.dist-info/METADATA
obs_tools-0.0.4.dist-info/RECORD
obs_tools-0.0.4.dist-info/WHEEL
obs_tools-0.0.4.dist-info/metadata.json
obs_tools-0.0.4.dist-info/top_level.txt
