Metadata-Version: 2.0
Name: obs-tools
Version: 0.0.4
Summary: A collection of useful scripts
Home-page: https://github.org/unfoldingWord-dev/obs_tools
Author: unfoldingWord
Author-email: phillip_hopper@wycliffeassociates.org
License: MIT
Keywords: unfoldingWord obs tools
Platform: UNKNOWN
